c2puml/__init__.py
c2puml/config.py
c2puml/main.py
c2puml/models.py
c2puml/utils.py
c2puml/core/__init__.py
c2puml/core/generator.py
c2puml/core/parse_utils.py
c2puml/core/parser.py
c2puml/core/parser_anonymous_processor.py
c2puml/core/parser_tokenizer.py
c2puml/core/preprocessor.py
c2puml/core/transformer.py
c2puml/core/verifier.py
c2puml-2025.9.14.2.dist-info/licenses/LICENSE
c2puml-2025.9.14.2.dist-info/METADATA
c2puml-2025.9.14.2.dist-info/WHEEL
c2puml-2025.9.14.2.dist-info/entry_points.txt
c2puml-2025.9.14.2.dist-info/top_level.txt
c2puml-2025.9.14.2.dist-info/RECORD
