Metadata-Version: 2.4
Name: c2puml
Version: 2025.9.14.2
Summary: Convert C/C++ code to PlantUML diagrams with advanced filtering and transformation capabilities
Author-email: C to PlantUML Team <fischerjooo@users.noreply.github.com>
License: MIT
Project-URL: Homepage, https://github.com/fischerjooo/c2puml
Project-URL: Repository, https://github.com/fischerjooo/c2puml
Project-URL: Issues, https://github.com/fischerjooo/c2puml/issues
Project-URL: Documentation, https://fischerjooo.github.io/c2puml
Project-URL: Download ZIP, https://github.com/fischerjooo/c2puml/archive/refs/heads/release.zip
Project-URL: Download TAR.GZ, https://github.com/fischerjooo/c2puml/archive/refs/heads/release.tar.gz
Keywords: c,cpp,plantuml,uml,diagram,code-generation,documentation
Classifier: Development Status :: 4 - Beta
Classifier: Intended Audience :: Developers
Classifier: License :: OSI Approved :: MIT License
Classifier: Operating System :: OS Independent
Classifier: Programming Language :: Python :: 3
Classifier: Programming Language :: Python :: 3.7
Classifier: Programming Language :: Python :: 3.8
Classifier: Programming Language :: Python :: 3.9
Classifier: Programming Language :: Python :: 3.10
Classifier: Programming Language :: Python :: 3.11
Classifier: Programming Language :: Python :: 3.12
Classifier: Programming Language :: Python :: 3.13
Classifier: Topic :: Software Development :: Documentation
Classifier: Topic :: Software Development :: Libraries :: Python Modules
Classifier: Topic :: Software Development :: Code Generators
Classifier: Topic :: Documentation
Requires-Python: >=3.7
License-File: LICENSE
Dynamic: license-file
